sphinxcontrib/jquery/__init__.py
sphinxcontrib/jquery/_sphinx_javascript_frameworks_compat.js
sphinxcontrib/jquery/jquery-3.6.0.js
sphinxcontrib/jquery/jquery.js
sphinxcontrib_jquery-4.0.dist-info/WHEEL
sphinxcontrib_jquery-4.0.dist-info/METADATA
sphinxcontrib_jquery-4.0.dist-info/RECORD
