Metadata-Version: 2.1
Name: sphinxcontrib-jquery
Version: 4.0
Summary: Extension to include jQuery on newer Sphinx releases
Author: Adam Turner
Requires-Python: >=2.7
Classifier: Development Status :: 5 - Production/Stable
Classifier: License :: OSI Approved :: BSD License
Classifier: Operating System :: OS Independent
Classifier: Programming Language :: Python
Classifier: Programming Language :: Python :: 2
Classifier: Programming Language :: Python :: 3
Classifier: Programming Language :: Python :: 2.7
Classifier: Programming Language :: Python :: 3.5
Classifier: Programming Language :: Python :: 3.6
Classifier: Programming Language :: Python :: 3.7
Classifier: Programming Language :: Python :: 3.8
Classifier: Programming Language :: Python :: 3.9
Classifier: Programming Language :: Python :: 3.10
Classifier: Programming Language :: Python :: 3.11
Classifier: Programming Language :: Python :: Implementation :: CPython
Classifier: Programming Language :: Python :: Implementation :: PyPy
Classifier: Framework :: Sphinx
Classifier: Framework :: Sphinx :: Extension
Classifier: Topic :: Documentation
Classifier: Topic :: Documentation :: Sphinx
Requires-Dist: Sphinx>=1.8
Project-URL: Repository, https://github.com/sphinx-contrib/jquery/
